aio_rabbitmq_utils/__init__.py
aio_rabbitmq_utils/base_device.py
aio_rabbitmq_utils/base_device_manager.py
aio_rabbitmq_utils/consume_input_device_manager.py
aio_rabbitmq_utils/create_queue.py
aio_rabbitmq_utils/device_manager.py
aio_rabbitmq_utils/input_consume_device.py
aio_rabbitmq_utils/input_device.py
aio_rabbitmq_utils/multi_connection_device_manager.py
aio_rabbitmq_utils/multi_connection_input_device_manager.py
aio_rabbitmq_utils/output_device.py
aio_rabbitmq_utils/output_device_manager.py
aio_rabbitmq_utils/transaction.py
aio_rabbitmq_utils-1.0.13.dist-info/licenses/LICENSE
aio_rabbitmq_utils-1.0.13.dist-info/METADATA
aio_rabbitmq_utils-1.0.13.dist-info/WHEEL
aio_rabbitmq_utils-1.0.13.dist-info/top_level.txt
aio_rabbitmq_utils-1.0.13.dist-info/RECORD
