Metadata-Version: 2.4
Name: aio-rabbitmq-utils
Version: 1.0.13
Summary: A package for async communication with RabbitMQ
Author-email: Omer Dagry <omerdagry@gmail.com>
License: MIT License
Project-URL: Homepage, https://github.com/Omer-Dagry/RabbitMQUtils
Project-URL: Issues, https://github.com/Omer-Dagry/RabbitMQUtils/issues
Keywords: rabbitmq,pika,aio,async
Classifier: Operating System :: OS Independent
Classifier: License :: OSI Approved :: MIT License
Classifier: Programming Language :: Python :: 3.10
Classifier: Programming Language :: Python :: 3.11
Classifier: Programming Language :: Python :: 3.12
Requires-Python: >=3.10
License-File: LICENSE
Requires-Dist: aio-pika==9.*
Requires-Dist: no-exception==1.*
Dynamic: license-file
